{
  "best": {
    "params": {
      "ma_type": "RMA",
      "ma_source": "hlc3",
      "std_ma_type": "NWMA_TRIA",
      "std_source": "low",
      "ma_period": 1484,
      "std_ma_period": 614
    },
    "score": 2.465163288529699,
    "abs_corr": 2.465163288529699
  },
  "population": {
    "base_pop_size": 512,
    "adjusted_pop_size": 445
  },
  "proxy_target": {
    "horizon_minutes": 7,
    "price_col": "Close"
  },
  "metric": {
    "name": "extremes_vs_mid_ir_oof",
    "segments_count": 20,
    "train_frac": 0.8,
    "gap": 2000,
    "stat": "median",
    "clip_q": 0.01,
    "min_bucket_size": 600,
    "min_valid_segments": 19,
    "q_ext": 0.2,
    "q_mid": 0.25
  },
  "fit_config_hash": "271e8bc68c590783"
}